{
"Actor": {
  "types": ["PC", "NPC", "Enemy"],
  "templates": {
    "background": {
      "biography": ""
    },
 "abilities": {
 	"str":{
 		"value": 10,
 		"proficient": 0,
 		"max": null
 		},
	"dex":{
 		"value": 10,
 		"proficient": 0,
 		"max": null
 		},
 	"int":{
 		"value": 10,
 		"proficient": 0,
 		"max": null
 		},
 	"cha":{
 		"value": 10,
 		"proficient": 0,
 		"max": null
 		},
 	"per":{
 		"value": 10,
 		"proficient": 0,
 		"max": null
 		}
 	},
 	 "attributes":{
 	 	"ac": {
            "flat": null,
            "calc": "default",
            "formula": ""
          },
          "hp": {
            "value": 10,
            "max": null,
          },
          "mana": {
            "value": 10,
            "max": null,
          },
          "init": {
            "ability": "",
            "bonus": ""
          },
          "movement": {
            "burrow": 0,
            "climb": 0,
            "fly": 0,
            "swim": 0,
            "walk": 30,
            "units": "ft",
            "hover": false
          },
          "exhaust":{"value":0,
          			"max":8}

 	 },

 	  "details": {
          "biography": {
            "value": "",
            "public": ""
          },

		"currency": {
          "pp": 0,
          "gp": 0,
          "sp": 0,
          "cp": 0
        }

 },

}